Metadata-Version: 1.2
Name: ngslite
Version: 1.2.1
Summary: Light-weight functions for next-generation sequencing (NGS) data analysis
Home-page: https://github.com/linyc74/ngslite
Author: Yu-Cheng Lin
Author-email: yclin.python@gmail.com
License: MIT
Platform: UNKNOWN
Requires-Python: >3.6
